flask_authoob/__init__.py
flask_authoob/email_provider.py
flask_authoob/hooks.py
flask_authoob/routes.py
Flask_AuthOOB-0.0.34.dist-info/LICENSE
Flask_AuthOOB-0.0.34.dist-info/METADATA
Flask_AuthOOB-0.0.34.dist-info/WHEEL
Flask_AuthOOB-0.0.34.dist-info/top_level.txt
Flask_AuthOOB-0.0.34.dist-info/RECORD
