Metadata-Version: 2.1
Name: Flask-AuthOOB
Version: 0.0.34
Summary: Implement quiclky authentification in flask using postgres and flask-security
Home-page: UNKNOWN
Author: Eric Régnier
Author-email: utopman@gmail.com
License: MIT
Keywords: web,authentification,jwt,flask,api
Platform: UNKNOWN
Classifier: Programming Language :: Python
Classifier: Programming Language :: Python :: 3.6
Classifier: Programming Language :: Python :: 3.7
Classifier: Programming Language :: Python :: Implementation :: PyPy
Classifier: Programming Language :: Python :: Implementation :: Jython
Classifier: Intended Audience :: Developers
Requires-Dist: Flask
Requires-Dist: flask-sqlalchemy
Requires-Dist: sendgrid
Requires-Dist: Flask-Marshmallow
Requires-Dist: validate-email
Requires-Dist: password-strength
Requires-Dist: bcrypt
Requires-Dist: psycopg2-binary
Requires-Dist: marshmallow-sqlalchemy
Requires-Dist: flask-security-too (==3.2.0rc1)
